pytrust/__init__.py
pytrust/__main__.py
pytrust/_version.py
pytrust/cli.py
pytrust/permissions.py
pytrust-0.2.6.dist-info/entry_points.txt
pytrust-0.2.6.dist-info/WHEEL
pytrust-0.2.6.dist-info/METADATA
pytrust-0.2.6.dist-info/RECORD
