Metadata-Version: 2.1
Name: pytrust
Version: 0.2.6
Summary: CLI tool to check package permissions.
Author-email: Martin Thoma <info@martin-thoma.de>
Requires-Python: >=3.8
Requires-Dist: pyyaml
Requires-Dist: click
Requires-Dist: importlib-metadata; python_version<'3.8'
